ray_vllm/__init__.py
ray_vllm/deploy.py
ray_vllm/vllm_model.py
ray_vllm-0.9.7.dist-info/METADATA
ray_vllm-0.9.7.dist-info/WHEEL
ray_vllm-0.9.7.dist-info/top_level.txt
ray_vllm-0.9.7.dist-info/RECORD
