Metadata-Version: 2.4
Name: ray-vllm
Version: 0.9.7
Summary: Deploy vLLM models to a ray cluster
Author: Crispin Almodovar
Author-email: crispin.almodovar@docorto.ai
Classifier: Programming Language :: Python :: 3
Classifier: License :: OSI Approved :: MIT License
Classifier: Operating System :: OS Independent
Requires-Python: >=3.12
